{
  "source": "https://api.flyingtulip.com/status/put/dashboard",
  "updatedAt": "2026-04-09T20:15:46.797Z",
  "upstreamUpdatedAt": "2026-04-09T20:15:17Z",
  "rpcSource": "https://eth-mainnet.g.alchemy.com/v2/nkFvhGGraxX6SO4j2oEn4",
  "systemNav": {
    "value": 0.10153586963537764,
    "display": "$0.10154"
  },
  "withdrawalNav": {
    "value": 0.08027956155565621,
    "display": "$0.08028"
  },
  "inputs": {
    "totalCollateralUsd": 113091964.00999999,
    "ftAllocated": 1113812925.5810885,
    "ftWithdrawn": 30330625.06523086,
    "withdrawalComponentsUsd": {
      "stable": 1760516.3742,
      "wethHistoricalMark": 674412.90774573
    },
    "withdrawalComponentsAmount": {
      "usdc": "1238737.719956",
      "usdt": "521778.654244",
      "weth": "331.75818985"
    },
    "withdrawalScanState": {
      "fromBlock": "24844166",
      "toBlock": "24844486",
      "lastProcessedBlock": "24844486"
    }
  }
}
