{
  "source": "https://api.flyingtulip.com/status/put/dashboard",
  "updatedAt": "2026-04-07T17:38:00.966Z",
  "upstreamUpdatedAt": "2026-04-07T17:37:13Z",
  "rpcSource": "https://eth-mainnet.g.alchemy.com/v2/nkFvhGGraxX6SO4j2oEn4",
  "systemNav": {
    "value": 0.10038622158300235,
    "display": "$0.10039"
  },
  "withdrawalNav": {
    "value": 0.08575499558229314,
    "display": "$0.08575"
  },
  "inputs": {
    "totalCollateralUsd": 111914348.73999998,
    "ftAllocated": 1114837743.4194574,
    "ftWithdrawn": 28303517.44439616,
    "withdrawalComponentsUsd": {
      "stable": 1760516.3742,
      "wethHistoricalMark": 666651.63920755
    },
    "withdrawalComponentsAmount": {
      "usdc": "1238737.719956",
      "usdt": "521778.654244",
      "weth": "328.24399794"
    },
    "withdrawalScanState": {
      "fromBlock": "24828947",
      "toBlock": "24829350",
      "lastProcessedBlock": "24829350"
    }
  }
}
