{
  "source": "https://api.flyingtulip.com/status/put/dashboard",
  "updatedAt": "2026-04-12T14:11:54.960Z",
  "upstreamUpdatedAt": "2026-04-12T14:11:53Z",
  "rpcSource": "https://eth-mainnet.g.alchemy.com/v2/nkFvhGGraxX6SO4j2oEn4",
  "systemNav": {
    "value": 0.10165361793074108,
    "display": "$0.10165"
  },
  "withdrawalNav": {
    "value": 0.07493496289423139,
    "display": "$0.07493"
  },
  "inputs": {
    "totalCollateralUsd": 100040067.95999998,
    "ftAllocated": 984126979.4072607,
    "ftWithdrawn": 33828391.76852215,
    "withdrawalComponentsUsd": {
      "stable": 1860516.3742,
      "wethHistoricalMark": 674412.90774573
    },
    "withdrawalComponentsAmount": {
      "usdc": "1238737.719956",
      "usdt": "621778.654244",
      "weth": "331.75818985"
    },
    "withdrawalScanState": {
      "fromBlock": "24863881",
      "toBlock": "24864188",
      "lastProcessedBlock": "24864188"
    }
  }
}
